chzzkapi/__init__.py
chzzkapi/chzzkapi.py
chzzkapi-0.2.dist-info/LICENSE
chzzkapi-0.2.dist-info/METADATA
chzzkapi-0.2.dist-info/WHEEL
chzzkapi-0.2.dist-info/top_level.txt
chzzkapi-0.2.dist-info/RECORD
