Metadata-Version: 2.1
Name: chzzkapi
Version: 0.2
Summary: Chzzk API Python package
Home-page: https://github.com/KKoble/chzzkpy
Author: Koble
Author-email: kimkoble4@gmail.com
Classifier: Programming Language :: Python :: 3
Classifier: License :: OSI Approved :: MIT License
Classifier: Operating System :: OS Independent
License-File: LICENSE
Requires-Dist: requests
